odoo/addons/product_sold_by_delivery_week/README.rst
odoo/addons/product_sold_by_delivery_week/__init__.py
odoo/addons/product_sold_by_delivery_week/__manifest__.py
odoo/addons/product_sold_by_delivery_week/hooks.py
odoo/addons/product_sold_by_delivery_week/data/ir_cron.xml
odoo/addons/product_sold_by_delivery_week/i18n/es.po
odoo/addons/product_sold_by_delivery_week/i18n/it.po
odoo/addons/product_sold_by_delivery_week/i18n/product_sold_by_delivery_week.pot
odoo/addons/product_sold_by_delivery_week/i18n/pt_BR.po
odoo/addons/product_sold_by_delivery_week/models/__init__.py
odoo/addons/product_sold_by_delivery_week/models/product_product.py
odoo/addons/product_sold_by_delivery_week/models/product_template.py
odoo/addons/product_sold_by_delivery_week/models/sale_order.py
odoo/addons/product_sold_by_delivery_week/models/stock_move.py
odoo/addons/product_sold_by_delivery_week/readme/CONFIGURE.md
odoo/addons/product_sold_by_delivery_week/readme/CONTRIBUTORS.md
odoo/addons/product_sold_by_delivery_week/readme/DESCRIPTION.md
odoo/addons/product_sold_by_delivery_week/readme/ROADMAP.md
odoo/addons/product_sold_by_delivery_week/readme/USAGE.md
odoo/addons/product_sold_by_delivery_week/security/product_sold_by_delivery_week_security.xml
odoo/addons/product_sold_by_delivery_week/static/description/icon.png
odoo/addons/product_sold_by_delivery_week/static/description/index.html
odoo/addons/product_sold_by_delivery_week/static/description/sold_by_week_hint.png
odoo/addons/product_sold_by_delivery_week/tests/__init__.py
odoo/addons/product_sold_by_delivery_week/tests/test_product_sold_by_delivery_week.py
odoo/addons/product_sold_by_delivery_week/views/product_views.xml
odoo/addons/product_sold_by_delivery_week/views/sale_views.xml
odoo_addon_product_sold_by_delivery_week-18.0.1.0.0.2.dist-info/METADATA
odoo_addon_product_sold_by_delivery_week-18.0.1.0.0.2.dist-info/WHEEL
odoo_addon_product_sold_by_delivery_week-18.0.1.0.0.2.dist-info/top_level.txt
odoo_addon_product_sold_by_delivery_week-18.0.1.0.0.2.dist-info/RECORD
